petrobuffer/__init__.py
petrobuffer/buffers.py
petrobuffer/conversions.py
petrobuffer/core.py
petrobuffer/ferric.py
petrobuffer-0.0.1.dist-info/LICENSE
petrobuffer-0.0.1.dist-info/WHEEL
petrobuffer-0.0.1.dist-info/METADATA
petrobuffer-0.0.1.dist-info/RECORD
