Metadata-Version: 2.1
Name: petrobuffer
Version: 0.0.1
Summary: PetroBuffer
Author-email: Philippa Liggins <pkl28@cam.ac.uk>
Requires-Python: >=3.7
Classifier: License :: OSI Approved :: MIT License
Classifier: Programming Language :: Python :: 3
Requires-Dist: numpy>=1.15.3
Requires-Dist: sphinx == 5.0.2 ; extra == "doc"
Requires-Dist: pytest >= 7.1.2 ; extra == "test"
Project-URL: Home, https://github.com/pipliggins/PetroBuffer
Provides-Extra: doc
Provides-Extra: test
